ilovebandits/__init__.py
ilovebandits/agents.py
ilovebandits/exceptions.py
ilovebandits/handlers.py
ilovebandits/sim.py
ilovebandits/utils.py
ilovebandits/data_bandits/__init__.py
ilovebandits/data_bandits/base.py
ilovebandits/data_bandits/utils.py
ilovebandits/mab/__init__.py
ilovebandits/mab/agents.py
ilovebandits/mab/q_estimators.py
ilovebandits/mab/utils.py
ilovebandits/tests/conftest.py
ilovebandits/tests/reqs_test_github.txt
ilovebandits/tests/reqs_tests.txt
ilovebandits/tests/cbandits/notes_launch_tests.txt
ilovebandits/tests/cbandits/test_agents.py
ilovebandits/tests/cbandits/test_databandits.py
ilovebandits/tests/cbandits/test_handlers.py
ilovebandits/tests/cbandits/test_sim.py
ilovebandits/tests/cbandits/test_utils.py
ilovebandits-0.1.1.dist-info/METADATA
ilovebandits-0.1.1.dist-info/WHEEL
ilovebandits-0.1.1.dist-info/licenses/LICENSE
ilovebandits-0.1.1.dist-info/RECORD
