Metadata-Version: 2.4
Name: ilovebandits
Version: 0.1.1
Summary: Advanced features for bandits with or without context.
Project-URL: Homepage, https://github.com/Abel-24pal/ilovebandits
Project-URL: Repository, https://github.com/Abel-24pal/ilovebandits
Author-email: Abel Sancarlos Gonzalez <abel.ingelectrico@gmail.com>
License: Apache-2.0
License-File: LICENSE
Keywords: contextual bandits,data-driven decision engines,mab,machine learning,python
Classifier: Development Status :: 2 - Pre-Alpha
Classifier: License :: OSI Approved :: Apache Software License
Classifier: Operating System :: Microsoft :: Windows
Classifier: Operating System :: Unix
Classifier: Programming Language :: Python
Classifier: Topic :: Scientific/Engineering
Requires-Python: >=3.10
Requires-Dist: pandas<2.4,>=2.2
Requires-Dist: scikit-learn>=1.5
Requires-Dist: unlzw3<1.0
Provides-Extra: dev
Requires-Dist: pytest-cov>=5.0.0; extra == 'dev'
Requires-Dist: pytest>=8.3.2; extra == 'dev'
Requires-Dist: ruff>=0.5.7; extra == 'dev'
